cork/__init__.py
cork/__main__.py
cork/browsers/browsh_darwin
cork/browsers/browsh_freebsd
cork/browsers/browsh_linux
cork/browsers/browsh_openbsd
cork/browsers/browsh_win32
cork-0.2.dist-info/LICENSE
cork-0.2.dist-info/METADATA
cork-0.2.dist-info/WHEEL
cork-0.2.dist-info/entry_points.txt
cork-0.2.dist-info/top_level.txt
cork-0.2.dist-info/RECORD
