Metadata-Version: 2.1
Name: cork
Version: 0.2
Summary: UNKNOWN
Home-page: https://github.com/psbleep/cork
Author: Patrick Schneeweis
Author-email: psbleep@protonmail.com
License: GPLv3+
Platform: UNKNOWN
Requires-Dist: Click (==7.0)
Requires-Dist: Flask (==1.0.2)
Requires-Dist: PyInstaller (==3.4)
Requires-Dist: requests (==2.21.0)
